ec2/__init__.py
ec2/__main__.py
ec2/logging.ini
ec2/main.py
ec2/utils.py
ec2.py-0.1.4.dist-info/DESCRIPTION.rst
ec2.py-0.1.4.dist-info/entry_points.txt
ec2.py-0.1.4.dist-info/METADATA
ec2.py-0.1.4.dist-info/metadata.json
ec2.py-0.1.4.dist-info/RECORD
ec2.py-0.1.4.dist-info/top_level.txt
ec2.py-0.1.4.dist-info/WHEEL
