Metadata-Version: 2.0
Name: ec2.py
Version: 0.1.4
Summary: Simple CLI / module to create/start/stop EC2 instances
Home-page: https://github.com/khilnani/ec2.py
Author: khilnani
Author-email: nik@khilnani.org
License: MIT
Keywords: utility,api,ec2,aws,helper
Platform: UNKNOWN
Classifier: Development Status :: 3 - Alpha
Classifier: Environment :: Console
Classifier: Environment :: Console
Classifier: Intended Audience :: Developers
Classifier: Intended Audience :: System Administrators
Classifier: License :: OSI Approved :: MIT License
Classifier: Operating System :: MacOS :: MacOS X
Classifier: Operating System :: Unix
Classifier: Operating System :: POSIX
Classifier: Programming Language :: Python
Classifier: Programming Language :: Python :: 2.7
Classifier: Topic :: Software Development
Classifier: Topic :: Software Development :: Libraries
Classifier: Topic :: Software Development :: Libraries :: Python Modules
Requires-Dist: boto3
